Workbook

Sheet P&L
A1: Parts of Practice — 2026 Profit & Loss by Month
A2: GroupRB — Jan–Sep 2026 · all customers
B4: 46023 | C4: 46054 | D4: 46082 | E4: 46113 | F4: 46143 | G4: 46174 | H4: 46204 | I4: 46235 | J4: 46266 | K4: Total
A5: Revenue
A6: Membership Fee ($99/mo) | B6: =SUMIFS('Revenue Detail'!$D:$D,'Revenue Detail'!$C:$C,"Membership Fee",'Revenue Detail'!$A:$A,">="&B$4,'Revenue Detail'!$A:$A,"<"&EDATE(B$4,1)) | C6: =SUMIFS('Revenue Detail'!$D:$D,'Revenue Detail'!$C:$C,"Membership Fee",'Revenue Detail'!$A:$A,">="&C$4,'Revenue Detail'!$A:$A,"<"&EDATE(C$4,1)) | D6: =SUMIFS('Revenue Detail'!$D:$D,'Revenue Detail'!$C:$C,"Membership Fee",'Revenue Detail'!$A:$A,">="&D$4,'Revenue Detail'!$A:$A,"<"&EDATE(D$4,1)) | E6: =SUMIFS('Revenue Detail'!$D:$D,'Revenue Detail'!$C:$C,"Membership Fee",'Revenue Detail'!$A:$A,">="&E$4,'Revenue Detail'!$A:$A,"<"&EDATE(E$4,1)) | F6: =SUMIFS('Revenue Detail'!$D:$D,'Revenue Detail'!$C:$C,"Membership Fee",'Revenue Detail'!$A:$A,">="&F$4,'Revenue Detail'!$A:$A,"<"&EDATE(F$4,1)) | G6: =SUMIFS('Revenue Detail'!$D:$D,'Revenue Detail'!$C:$C,"Membership Fee",'Revenue Detail'!$A:$A,">="&G$4,'Revenue Detail'!$A:$A,"<"&EDATE(G$4,1)) | H6: =SUMIFS('Revenue Detail'!$D:$D,'Revenue Detail'!$C:$C,"Membership Fee",'Revenue Detail'!$A:$A,">="&H$4,'Revenue Detail'!$A:$A,"<"&EDATE(H$4,1)) | I6: =SUMIFS('Revenue Detail'!$D:$D,'Revenue Detail'!$C:$C,"Membership Fee",'Revenue Detail'!$A:$A,">="&I$4,'Revenue Detail'!$A:$A,"<"&EDATE(I$4,1)) | J6: =SUMIFS('Revenue Detail'!$D:$D,'Revenue Detail'!$C:$C,"Membership Fee",'Revenue Detail'!$A:$A,">="&J$4,'Revenue Detail'!$A:$A,"<"&EDATE(J$4,1)) | K6: =SUM(B6:J6)
A7: Total Revenue | B7: =SUM(B6:B6) | C7: =SUM(C6:C6) | D7: =SUM(D6:D6) | E7: =SUM(E6:E6) | F7: =SUM(F6:F6) | G7: =SUM(G6:G6) | H7: =SUM(H6:H6) | I7: =SUM(I6:I6) | ... K7: =SUM(K6:K6)
A9: Expenses
A10: Hosting | B10: =SUMIFS('Expense Detail'!$D:$D,'Expense Detail'!$C:$C,"Hosting",'Expense Detail'!$A:$A,">="&B$4,'Expense Detail'!$A:$A,"<"&EDATE(B$4,1)) | C10: =SUMIFS('Expense Detail'!$D:$D,'Expense Detail'!$C:$C,"Hosting",'Expense Detail'!$A:$A,">="&C$4,'Expense Detail'!$A:$A,"<"&EDATE(C$4,1)) | D10: =SUMIFS('Expense Detail'!$D:$D,'Expense Detail'!$C:$C,"Hosting",'Expense Detail'!$A:$A,">="&D$4,'Expense Detail'!$A:$A,"<"&EDATE(D$4,1)) | E10: =SUMIFS('Expense Detail'!$D:$D,'Expense Detail'!$C:$C,"Hosting",'Expense Detail'!$A:$A,">="&E$4,'Expense Detail'!$A:$A,"<"&EDATE(E$4,1)) | F10: =SUMIFS('Expense Detail'!$D:$D,'Expense Detail'!$C:$C,"Hosting",'Expense Detail'!$A:$A,">="&F$4,'Expense Detail'!$A:$A,"<"&EDATE(F$4,1)) | G10: =SUMIFS('Expense Detail'!$D:$D,'Expense Detail'!$C:$C,"Hosting",'Expense Detail'!$A:$A,">="&G$4,'Expense Detail'!$A:$A,"<"&EDATE(G$4,1)) | H10: =SUMIFS('Expense Detail'!$D:$D,'Expense Detail'!$C:$C,"Hosting",'Expense Detail'!$A:$A,">="&H$4,'Expense Detail'!$A:$A,"<"&EDATE(H$4,1)) | I10: =SUMIFS('Expense Detail'!$D:$D,'Expense Detail'!$C:$C,"Hosting",'Expense Detail'!$A:$A,">="&I$4,'Expense Detail'!$A:$A,"<"&EDATE(I$4,1)) | J10: =SUMIFS('Expense Detail'!$D:$D,'Expense Detail'!$C:$C,"Hosting",'Expense Detail'!$A:$A,">="&J$4,'Expense Detail'!$A:$A,"<"&EDATE(J$4,1)) | K10: =SUM(B10:J10)
A11: Seobility | B11: =SUMIFS('Expense Detail'!$D:$D,'Expense Detail'!$C:$C,"Seobility",'Expense Detail'!$A:$A,">="&B$4,'Expense Detail'!$A:$A,"<"&EDATE(B$4,1)) | C11: =SUMIFS('Expense Detail'!$D:$D,'Expense Detail'!$C:$C,"Seobility",'Expense Detail'!$A:$A,">="&C$4,'Expense Detail'!$A:$A,"<"&EDATE(C$4,1)) | D11: =SUMIFS('Expense Detail'!$D:$D,'Expense Detail'!$C:$C,"Seobility",'Expense Detail'!$A:$A,">="&D$4,'Expense Detail'!$A:$A,"<"&EDATE(D$4,1)) | E11: =SUMIFS('Expense Detail'!$D:$D,'Expense Detail'!$C:$C,"Seobility",'Expense Detail'!$A:$A,">="&E$4,'Expense Detail'!$A:$A,"<"&EDATE(E$4,1)) | F11: =SUMIFS('Expense Detail'!$D:$D,'Expense Detail'!$C:$C,"Seobility",'Expense Detail'!$A:$A,">="&F$4,'Expense Detail'!$A:$A,"<"&EDATE(F$4,1)) | G11: =SUMIFS('Expense Detail'!$D:$D,'Expense Detail'!$C:$C,"Seobility",'Expense Detail'!$A:$A,">="&G$4,'Expense Detail'!$A:$A,"<"&EDATE(G$4,1)) | H11: =SUMIFS('Expense Detail'!$D:$D,'Expense Detail'!$C:$C,"Seobility",'Expense Detail'!$A:$A,">="&H$4,'Expense Detail'!$A:$A,"<"&EDATE(H$4,1)) | I11: =SUMIFS('Expense Detail'!$D:$D,'Expense Detail'!$C:$C,"Seobility",'Expense Detail'!$A:$A,">="&I$4,'Expense Detail'!$A:$A,"<"&EDATE(I$4,1)) | J11: =SUMIFS('Expense Detail'!$D:$D,'Expense Detail'!$C:$C,"Seobility",'Expense Detail'!$A:$A,">="&J$4,'Expense Detail'!$A:$A,"<"&EDATE(J$4,1)) | K11: =SUM(B11:J11)
A12: Ubersuggest | B12: =SUMIFS('Expense Detail'!$D:$D,'Expense Detail'!$C:$C,"Ubersuggest",'Expense Detail'!$A:$A,">="&B$4,'Expense Detail'!$A:$A,"<"&EDATE(B$4,1)) | C12: =SUMIFS('Expense Detail'!$D:$D,'Expense Detail'!$C:$C,"Ubersuggest",'Expense Detail'!$A:$A,">="&C$4,'Expense Detail'!$A:$A,"<"&EDATE(C$4,1)) | D12: =SUMIFS('Expense Detail'!$D:$D,'Expense Detail'!$C:$C,"Ubersuggest",'Expense Detail'!$A:$A,">="&D$4,'Expense Detail'!$A:$A,"<"&EDATE(D$4,1)) | E12: =SUMIFS('Expense Detail'!$D:$D,'Expense Detail'!$C:$C,"Ubersuggest",'Expense Detail'!$A:$A,">="&E$4,'Expense Detail'!$A:$A,"<"&EDATE(E$4,1)) | F12: =SUMIFS('Expense Detail'!$D:$D,'Expense Detail'!$C:$C,"Ubersuggest",'Expense Detail'!$A:$A,">="&F$4,'Expense Detail'!$A:$A,"<"&EDATE(F$4,1)) | G12: =SUMIFS('Expense Detail'!$D:$D,'Expense Detail'!$C:$C,"Ubersuggest",'Expense Detail'!$A:$A,">="&G$4,'Expense Detail'!$A:$A,"<"&EDATE(G$4,1)) | H12: =SUMIFS('Expense Detail'!$D:$D,'Expense Detail'!$C:$C,"Ubersuggest",'Expense Detail'!$A:$A,">="&H$4,'Expense Detail'!$A:$A,"<"&EDATE(H$4,1)) | I12: =SUMIFS('Expense Detail'!$D:$D,'Expense Detail'!$C:$C,"Ubersuggest",'Expense Detail'!$A:$A,">="&I$4,'Expense Detail'!$A:$A,"<"&EDATE(I$4,1)) | J12: =SUMIFS('Expense Detail'!$D:$D,'Expense Detail'!$C:$C,"Ubersuggest",'Expense Detail'!$A:$A,">="&J$4,'Expense Detail'!$A:$A,"<"&EDATE(J$4,1)) | K12: =SUM(B12:J12)
A13: Billing Fee | B13: =SUMIFS('Expense Detail'!$D:$D,'Expense Detail'!$C:$C,"Billing Fee",'Expense Detail'!$A:$A,">="&B$4,'Expense Detail'!$A:$A,"<"&EDATE(B$4,1)) | C13: =SUMIFS('Expense Detail'!$D:$D,'Expense Detail'!$C:$C,"Billing Fee",'Expense Detail'!$A:$A,">="&C$4,'Expense Detail'!$A:$A,"<"&EDATE(C$4,1)) | D13: =SUMIFS('Expense Detail'!$D:$D,'Expense Detail'!$C:$C,"Billing Fee",'Expense Detail'!$A:$A,">="&D$4,'Expense Detail'!$A:$A,"<"&EDATE(D$4,1)) | E13: =SUMIFS('Expense Detail'!$D:$D,'Expense Detail'!$C:$C,"Billing Fee",'Expense Detail'!$A:$A,">="&E$4,'Expense Detail'!$A:$A,"<"&EDATE(E$4,1)) | F13: =SUMIFS('Expense Detail'!$D:$D,'Expense Detail'!$C:$C,"Billing Fee",'Expense Detail'!$A:$A,">="&F$4,'Expense Detail'!$A:$A,"<"&EDATE(F$4,1)) | G13: =SUMIFS('Expense Detail'!$D:$D,'Expense Detail'!$C:$C,"Billing Fee",'Expense Detail'!$A:$A,">="&G$4,'Expense Detail'!$A:$A,"<"&EDATE(G$4,1)) | H13: =SUMIFS('Expense Detail'!$D:$D,'Expense Detail'!$C:$C,"Billing Fee",'Expense Detail'!$A:$A,">="&H$4,'Expense Detail'!$A:$A,"<"&EDATE(H$4,1)) | I13: =SUMIFS('Expense Detail'!$D:$D,'Expense Detail'!$C:$C,"Billing Fee",'Expense Detail'!$A:$A,">="&I$4,'Expense Detail'!$A:$A,"<"&EDATE(I$4,1)) | J13: =SUMIFS('Expense Detail'!$D:$D,'Expense Detail'!$C:$C,"Billing Fee",'Expense Detail'!$A:$A,">="&J$4,'Expense Detail'!$A:$A,"<"&EDATE(J$4,1)) | K13: =SUM(B13:J13)
A14: Total Expenses | B14: =SUM(B10:B13) | C14: =SUM(C10:C13) | D14: =SUM(D10:D13) | E14: =SUM(E10:E13) | F14: =SUM(F10:F13) | G14: =SUM(G10:G13) | H14: =SUM(H10:H13) | I14: =SUM(I10:I13) | ... K14: =SUM(K10:K13)
A16: Net Income | B16: =B7-B14 | C16: =C7-C14 | D16: =D7-D14 | E16: =E7-E14 | F16: =F7-F14 | G16: =G7-G14 | H16: =H7-H14 | I16: =I7-I14 | ... K16: =K7-K14
A19: Notes / assumptions:
A20: - Membership Fee revenue is pulled directly from the recorded Invoice rows in Revenue-source.xlsx (actual invoice dates, not evenly smoothed).
A21: Feb and Apr show $0 because no invoice was recorded those months in the source file; Sep shows $0 because no Sep membership invoice has been recorded yet.
A22: - Hosting, Seobility, Ubersuggest and Billing Fee are GroupRB out-of-pocket costs to deliver Parts of Practice, entered per the schedule you gave:
A23: Hosting $10/mo and Billing Fee $3/mo — Andy Studer & Gratitude Jan-Sep, Guidance Through Grief Sep only.
A24: Seobility $5/mo and Ubersuggest $6/mo — Andy Studer & Gratitude only, Jan-Sep (not billed for Grief).
A25: - "Billing Fee" is my label for the $3/mo charge described as "monthly billing charge" — rename in the Expense Detail sheet if you use a different name internally.
A26: - All monthly charges are dated the 1st of the month per your instructions ("billed on the 1st").

Sheet Revenue Detail
A1: Date | B1: Customer | C1: Category | D1: Amount
A2: 46053 | B2: Andy Studer Therapy | C2: Membership Fee | D2: 99
A3: 46053 | B3: Gratitude and Growth Counseling LLC | C3: Membership Fee | D3: 99
A4: 46083 | B4: Andy Studer Therapy | C4: Membership Fee | D4: 99
A5: 46083 | B5: Gratitude and Growth Counseling LLC | C5: Membership Fee | D5: 99
A6: 46112 | B6: Andy Studer Therapy | C6: Membership Fee | D6: 99
A7: 46112 | B7: Gratitude and Growth Counseling LLC | C7: Membership Fee | D7: 99
A8: 46146 | B8: Andy Studer Therapy | C8: Membership Fee | D8: 99
A9: 46146 | B9: Gratitude and Growth Counseling LLC | C9: Membership Fee | D9: 99
A10: 46181 | B10: Andy Studer Therapy | C10: Membership Fee | D10: 99
A11: 46181 | B11: Gratitude and Growth Counseling LLC | C11: Membership Fee | D11: 99
A12: 46204 | B12: Andy Studer Therapy | C12: Membership Fee | D12: 99
A13: 46204 | B13: Gratitude and Growth Counseling LLC | C13: Membership Fee | D13: 99
... A16: 46239 | B16: Guidance Through Grief Counseling Center, PLLC | C16: Membership Fee | D16: 99

Sheet Expense Detail
A1: Date | B1: Customer | C1: Category | D1: Amount
A2: 46023 | B2: Andy Studer Therapy | C2: Billing Fee | D2: 3
A3: 46023 | B3: Gratitude and Growth Counseling LLC | C3: Billing Fee | D3: 3
A4: 46023 | B4: Andy Studer Therapy | C4: Hosting | D4: 10
A5: 46023 | B5: Gratitude and Growth Counseling LLC | C5: Hosting | D5: 10
A6: 46023 | B6: Andy Studer Therapy | C6: Seobility | D6: 5
A7: 46023 | B7: Gratitude and Growth Counseling LLC | C7: Seobility | D7: 5
A8: 46023 | B8: Andy Studer Therapy | C8: Ubersuggest | D8: 6
A9: 46023 | B9: Gratitude and Growth Counseling LLC | C9: Ubersuggest | D9: 6
A10: 46054 | B10: Andy Studer Therapy | C10: Billing Fee | D10: 3
A11: 46054 | B11: Gratitude and Growth Counseling LLC | C11: Billing Fee | D11: 3
A12: 46054 | B12: Andy Studer Therapy | C12: Hosting | D12: 10
A13: 46054 | B13: Gratitude and Growth Counseling LLC | C13: Hosting | D13: 10
... A75: 46266 | B75: Gratitude and Growth Counseling LLC | C75: Ubersuggest | D75: 6
