Workbook

Sheet Calculator
A1: Start Performance — AI Receptionist · Cost & Margin Calculator
A2: Blue cells are yours to change. Everything else recalculates automatically.
A4: INPUTS — change these
A5: Number of customers | B5: 25
A6: Avg forwarded calls / customer / month | B6: 80 | C6: missed/busy calls that reach the AI
A7: Monthly price / customer | B7: 29
A8: Fair-use call cap (reference only) | B8: 100 | C8: suggest capping the $29 Starter plan here
A10: COST ASSUMPTIONS — edit to your real rates
A11: Avg voicemail length (minutes) | B11: 0.75
A12: Twilio voice + recording ($/min) | B12: 0.013
A13: Speech-to-text ($/min) | B13: 0.006 | C13: Deepgram / hosted Whisper
A14: Claude AI ($/call) | B14: 0.002 | C14: Haiku model, ~1 short call
A15: SMS ($/message) | B15: 0.01
A16: Messages per call | B16: 2 | C16: 1 to caller + 1 to the tradesperson
A17: Twilio phone number ($/mo per customer) | B17: 1.15
A18: A2P 10DLC registration ($/mo, total) | B18: 10 | C18: one shared cost, not per customer
A19: Server / hosting ($/mo, total) | B19: 12 | C19: your self-hosted box; set 0 if already owned
A20: Billing fee (% of price) | B20: 0.029 | C20: SwipePay/Stripe rate — check yours
A21: Billing fee ($/transaction) | B21: 0.3 | C21: set 0 during unpaid pilot
A23: PER-CALL COST
A24: Voice + recording / call | B24: =B11*B12 -> 0.00975
A25: Speech-to-text / call | B25: =B11*B13 -> 0.0045
A26: Claude / call | B26: =B14 -> 0.002
A27: SMS / call | B27: =B15*B16 -> 0.02
A28: Variable cost per call | B28: =SUM(B24:B27) -> 0.03625
A30: PER-CUSTOMER (per month)
A31: Phone number | B31: =B17 -> 1.15
A32: Call usage (calls × per-call) | B32: =B6*B28 -> 2.9
A33: Share of fixed costs | B33: =IFERROR((B18+B19)/B5,0) -> 0.88
A34: Billing fee | B34: =B7*B20+B21 -> 1.141
A35: Total cost per customer | B35: =SUM(B31:B34) -> 6.071
A36: Revenue per customer | B36: =B7 -> 29
A37: Gross profit per customer | B37: =B36-B35 -> 22.929
A38: Gross margin | B38: =IFERROR(B37/B36,0) -> 0.79065517
A40: BUSINESS TOTALS (per month)
A41: Total revenue | B41: =B5*B7 -> 725
A42: Total cost | B42: =B5*B35 -> 151.775
A43: Total gross profit | B43: =B41-B42 -> 573.225
A44: Overall gross margin | B44: =IFERROR(B43/B41,0) -> 0.79065517
A45: Annual gross profit | B45: =B43*12 -> 6878.7

Sheet Scenarios
A1: Scenarios — per-customer economics & scaling
A3: 1) Profit per customer by monthly call volume
A4: Scenario | B4: Calls / mo | C4: Usage | D4: Number | E4: Fixed share | F4: Billing | G4: Total cost | H4: Profit
A5: Light (part-time) | B5: 40 | C5: =B5*Calculator!$B$28 -> 1.45 | D5: =Calculator!$B$17 -> 1.15 | E5: =Calculator!$B$33 -> 0.88 | F5: =Calculator!$B$34 -> 1.141 | G5: =C5+D5+E5+F5 -> 4.621 | H5: =Calculator!$B$7-G5 -> 24.379
A6: Typical | B6: 80 | C6: =B6*Calculator!$B$28 -> 2.9 | D6: =Calculator!$B$17 -> 1.15 | E6: =Calculator!$B$33 -> 0.88 | F6: =Calculator!$B$34 -> 1.141 | G6: =C6+D6+E6+F6 -> 6.071 | H6: =Calculator!$B$7-G6 -> 22.929
A7: Busy shop | B7: 120 | C7: =B7*Calculator!$B$28 -> 4.35 | D7: =Calculator!$B$17 -> 1.15 | E7: =Calculator!$B$33 -> 0.88 | F7: =Calculator!$B$34 -> 1.141 | G7: =C7+D7+E7+F7 -> 7.521 | H7: =Calculator!$B$7-G7 -> 21.479
A8: Heavy | B8: 200 | C8: =B8*Calculator!$B$28 -> 7.25 | D8: =Calculator!$B$17 -> 1.15 | E8: =Calculator!$B$33 -> 0.88 | F8: =Calculator!$B$34 -> 1.141 | G8: =C8+D8+E8+F8 -> 10.421 | H8: =Calculator!$B$7-G8 -> 18.579
A10: Profit dips as call volume rises — the fair-use cap keeps heavy users on the right plan.
A12: 2) Monthly profit by customer count (at your typical call volume)
A13: Customers | B13: Revenue | C13: Variable cost | D13: Fixed cost | E13: Total cost | F13: Gross profit | G13: Margin
A14: 10 | B14: =A14*Calculator!$B$7 -> 290 | C14: =A14*(Calculator!$B$17+Calculator!$B$6*Calculator!$B$28+Calculator!$B$7*Calculator!$B$20+Calculator!$B$21) -> 51.91 | D14: =Calculator!$B$18+Calculator!$B$19 -> 22 | E14: =C14+D14 -> 73.91 | F14: =B14-E14 -> 216.09 | G14: =IFERROR(F14/B14,0) -> 0.74513793
A15: 25 | B15: =A15*Calculator!$B$7 -> 725 | C15: =A15*(Calculator!$B$17+Calculator!$B$6*Calculator!$B$28+Calculator!$B$7*Calculator!$B$20+Calculator!$B$21) -> 129.775 | D15: =Calculator!$B$18+Calculator!$B$19 -> 22 | E15: =C15+D15 -> 151.775 | F15: =B15-E15 -> 573.225 | G15: =IFERROR(F15/B15,0) -> 0.79065517
A16: 50 | B16: =A16*Calculator!$B$7 -> 1450 | C16: =A16*(Calculator!$B$17+Calculator!$B$6*Calculator!$B$28+Calculator!$B$7*Calculator!$B$20+Calculator!$B$21) -> 259.55 | D16: =Calculator!$B$18+Calculator!$B$19 -> 22 | E16: =C16+D16 -> 281.55 | F16: =B16-E16 -> 1168.45 | G16: =IFERROR(F16/B16,0) -> 0.80582759
A17: 100 | B17: =A17*Calculator!$B$7 -> 2900 | C17: =A17*(Calculator!$B$17+Calculator!$B$6*Calculator!$B$28+Calculator!$B$7*Calculator!$B$20+Calculator!$B$21) -> 519.1 | D17: =Calculator!$B$18+Calculator!$B$19 -> 22 | E17: =C17+D17 -> 541.1 | F17: =B17-E17 -> 2358.9 | G17: =IFERROR(F17/B17,0) -> 0.81341379
A18: 200 | B18: =A18*Calculator!$B$7 -> 5800 | C18: =A18*(Calculator!$B$17+Calculator!$B$6*Calculator!$B$28+Calculator!$B$7*Calculator!$B$20+Calculator!$B$21) -> 1038.2 | D18: =Calculator!$B$18+Calculator!$B$19 -> 22 | E18: =C18+D18 -> 1060.2 | F18: =B18-E18 -> 4739.8 | G18: =IFERROR(F18/B18,0) -> 0.8172069
A20: Margin improves as you scale — fixed costs (server + A2P) spread across more customers.

Sheet Tiered Plans
A1: Tiered Plans — blended margin across a customer mix
A2: Blue cells are yours. Cost rates are pulled live from the Calculator sheet.
A4: PLAN SETUP — change these
B5: Base plan | C5: Pro plan | D5: Blended / Total
A6: Monthly price | B6: 29 | C6: 79
A7: Typical calls / month | B7: 80 | C7: 250
A8: Included call cap | B8: 100 | C8: 400 | D8: soft cap for fair use
A9: Customers on this tier | B9: 40 | C9: 10
A11: PER-CUSTOMER ECONOMICS
B12: Base plan | C12: Pro plan | D12: Blended / Total
A13: Phone number | B13: =Calculator!$B$17 -> 1.15 | C13: =Calculator!$B$17 -> 1.15
A14: Call usage | B14: =B7*Calculator!$B$28 -> 2.9 | C14: =C7*Calculator!$B$28 -> 9.0625
A15: Share of fixed costs | B15: =IFERROR((Calculator!$B$18+Calculator!$B$19)/($B$9+$C$9),0) -> 0.44 | C15: =IFERROR((Calculator!$B$18+Calculator!$B$19)/($B$9+$C$9),0) -> 0.44
A16: Billing fee | B16: =B6*Calculator!$B$20+Calculator!$B$21 -> 1.141 | C16: =C6*Calculator!$B$20+Calculator!$B$21 -> 2.591
A17: Total cost / customer | B17: =B13+B14+B15+B16 -> 5.631 | C17: =C13+C14+C15+C16 -> 13.2435
A18: Profit / customer | B18: =B6-B17 -> 23.369 | C18: =C6-C17 -> 65.7565
A19: Margin | B19: =IFERROR(B18/B6,0) -> 0.80582759 | C19: =IFERROR(C18/C6,0) -> 0.83236076
A21: TOTALS (per month)
B22: Base plan | C22: Pro plan | D22: Blended / Total
A23: Customers | B23: =B9 -> 40 | C23: =C9 -> 10 | D23: =B9+C9 -> 50
A24: Revenue | B24: =B9*B6 -> 1160 | C24: =C9*C6 -> 790 | D24: =B24+C24 -> 1950
A25: Cost | B25: =B9*B17 -> 225.24 | C25: =C9*C17 -> 132.435 | D25: =B25+C25 -> 357.675
A26: Gross profit | B26: =B24-B25 -> 934.76 | C26: =C24-C25 -> 657.565 | D26: =B26+C26 -> 1592.325
A27: Margin | B27: =IFERROR(B26/B24,0) -> 0.80582759 | C27: =IFERROR(C26/C24,0) -> 0.83236076 | D27: =IFERROR(D26/D24,0) -> 0.81657692
A29: Blended profit / customer | D29: =IFERROR(D26/D23,0) -> 31.8465
A30: Annual gross profit | D30: =D26*12 -> 19107.9
A32: The Pro tier carries a higher margin AND more absolute profit — a few high-volume shops lift the whole blend.
